<?xml version="1.0" encoding="utf-8" ?>
<dwsync>
<file name="animation.css" server="157.65.23.133" local="133269600302270388" remote="133269609600000000" Dst="0" />
<file name="example-list.css" server="157.65.23.133" local="133225389387603252" remote="133233186000000000" Dst="0" />
<file name="example.css" server="157.65.23.133" local="133271243801881307" remote="133271437200000000" Dst="0" />
<file name="item-details.css" server="157.65.23.133" local="133227235794001418" remote="133233186000000000" Dst="0" />
<file name="main.css" server="157.65.23.133" local="133271215291222591" remote="133271437200000000" Dst="0" />
<file name="reset.css" server="157.65.23.133" local="133201236989713704" remote="133233186000000000" Dst="0" />
<file name="responsive.css" server="157.65.23.133" local="133271439339579259" remote="133271439600000000" Dst="0" />
<file name="animation.css" server="116.80.122.146" local="133294502477980777" remote="133469950800000000" Dst="0" />
<file name="example-list.css" server="116.80.122.146" local="133225389387603252" remote="133469950800000000" Dst="0" />
<file name="example.css" server="116.80.122.146" local="133271243801881307" remote="133469950800000000" Dst="0" />
<file name="item-details.css" server="116.80.122.146" local="133227235794001418" remote="133469950800000000" Dst="0" />
<file name="main.css" server="116.80.122.146" local="133378437140533455" remote="133378455000000000" Dst="0" />
<file name="reset.css" server="116.80.122.146" local="133201236989713704" remote="133469950800000000" Dst="0" />
<file name="responsive.css" server="116.80.122.146" local="133378453266693469" remote="133378455000000000" Dst="0" />
<file name="styles.css" server="116.80.122.146" local="133295365793122700" remote="133378455600000000" Dst="0" />
<file name="animation.css" server="27.34.163.53" local="133294502477980777" remote="133469998800000000" Dst="0" />
<file name="example-list.css" server="27.34.163.53" local="133225389387603252" remote="133469998800000000" Dst="0" />
<file name="example.css" server="27.34.163.53" local="133271243801881307" remote="133469998800000000" Dst="0" />
<file name="item-details.css" server="27.34.163.53" local="133227235794001418" remote="133469998800000000" Dst="0" />
<file name="main.css" server="27.34.163.53" local="133378437140533455" remote="133469998800000000" Dst="0" />
<file name="reset.css" server="27.34.163.53" local="133201236989713704" remote="133469998800000000" Dst="0" />
<file name="responsive.css" server="27.34.163.53" local="133378453266693469" remote="133469998800000000" Dst="0" />
<file name="styles.css" server="27.34.163.53" local="133295365793122700" remote="133469998800000000" Dst="0" />
</dwsync>